inspire/__init__.py
inspire/apps.py
inspire/management/__init__.py
inspire/management/commands/__init__.py
inspire/management/commands/inspire.py
django_inspire-0.0.3.dist-info/LICENSE.md
django_inspire-0.0.3.dist-info/METADATA
django_inspire-0.0.3.dist-info/WHEEL
django_inspire-0.0.3.dist-info/top_level.txt
django_inspire-0.0.3.dist-info/RECORD
