Metadata-Version: 2.1
Name: django-inspire
Version: 0.0.3
Summary: Inspiring Django Command.
Home-page: https://github.com/sawirricardo/django-inspire
Author: Ricardo Sawir
Author-email: sawir.ricardo@gmail.com
Requires-Python: >=2.7
License-File: LICENSE.md
Requires-Dist: Django (>=1.4)
